MANIFEST.in
README.md
requirements.txt
setup.py
pyquanta/__init__.py
pyquanta/except.py
pyquanta/exceptions.py
pyquanta.egg-info/PKG-INFO
pyquanta.egg-info/SOURCES.txt
pyquanta.egg-info/dependency_links.txt
pyquanta.egg-info/requires.txt
pyquanta.egg-info/top_level.txt
pyquanta/resources/__init__.py
pyquanta/resources/analytics.py
pyquanta/resources/base.py
pyquanta/resources/magento.py
pyquanta/resources/organization.py
pyquanta/resources/scenario.py
pyquanta/resources/site.py
pyquanta/resources/system.py
test/test.py