Metadata-Version: 1.1
Name: pyquanta
Version: 0.2.1
Summary: Pyquanta is a python module to interact with Quanta API
Home-page: https://github.com/quanta-computing/pyquanta
Author: Matthieu 'Korrigan' Rosinski
Author-email: mro@quanta-computing.com
License: MIT
Platform: UNKNOWN
Classifier: Development Status :: 4 - Beta
Classifier: Programming Language :: Python
Classifier: Programming Language :: Python :: 3
Classifier: Programming Language :: Python :: 2
Classifier: Intended Audience :: Developers
Classifier: Intended Audience :: System Administrators
Classifier: Operating System :: OS Independent
Classifier: License :: OSI Approved :: MIT License
Classifier: Topic :: Internet :: WWW/HTTP
Classifier: Topic :: Utilities
